AppOpener/__init__.py
AppOpener/__main__.py
AppOpener/check.py
AppOpener/commands.py
AppOpener/features.py
AppOpener/old_style.py
AppOpener/update_list.py
appopener-1.7.dist-info/LICENSE.txt
appopener-1.7.dist-info/METADATA
appopener-1.7.dist-info/WHEEL
appopener-1.7.dist-info/top_level.txt
appopener-1.7.dist-info/RECORD
