Metadata-Version: 2.1
Name: appopener
Version: 1.7
Summary: Open/Close any application by it's name.
Home-page: https://github.com/athrvvvv/AppOpener/tree/module
Download-URL: https://pypi.python.org/pypi/AppOpener
Author: Athrv Chaulkar
Author-email: athrvchaulkar@gmail.com
Maintainer: athrvvvv
Maintainer-email: athrvchaulkar@gmail.com
License: MIT
Project-URL: Documentation, https://appopener.readthedocs.io/en/latest/
Project-URL: Source, https://github.com/athrvvvv/AppOpener/tree/module
Project-URL: Tracker, https://github.com/athrvvvv/AppOpener/issues
Keywords: appopener,open apps,App Ids,automation,close apps
Platform: Windows 10
Platform: Windows 8.1
Platform: Windows 11
Classifier: Development Status :: 5 - Production/Stable
Classifier: Environment :: Console
Classifier: Operating System :: Microsoft :: Windows
Classifier: License :: OSI Approved :: MIT License
Classifier: Programming Language :: Python :: 3.5
Classifier: Programming Language :: Python :: 3.6
Classifier: Programming Language :: Python :: 3.7
Classifier: Programming Language :: Python :: 3.8
Classifier: Programming Language :: Python :: 3.9
Classifier: Programming Language :: Python :: 3.10
Classifier: Programming Language :: Python :: 3.11
License-File: LICENSE.txt
